ucdp_uvm-0.1.1.dist-info/METADATA
ucdp_uvm-0.1.1.dist-info/WHEEL
ucdp_uvm-0.1.1.dist-info/entry_points.txt
ucdp_uvm-0.1.1.dist-info/licenses/LICENSE
ucdp_uvm/__init__.py
ucdp_uvm/cfg.py
ucdp_uvm/env.py
ucdp_uvm/object.py
ucdp_uvm/scoreboard.py
ucdp_uvm/seq.py
ucdp_uvm/tb.py
ucdp_uvm/test.py
ucdp_uvm/vseq.py
ucdp_uvm-0.1.1.dist-info/RECORD
