Metadata-Version: 2.1
Name: ucdp-uvm
Version: 0.1.1
Summary: Unified Chip Design Environment - Unified Verification Methodology
Classifier: Programming Language :: Python :: 3
Classifier: Operating System :: OS Independent
Project-URL: Homepage, https://github.com/nbiotcloud/ucdp-uvm
Project-URL: Documentation, https://ucdp-uvm.readthedocs.io/en/stable/
Project-URL: Bug Tracker, https://github.com/nbiotcloud/ucdp-uvm/issues
Requires-Python: <4.0,>=3.10.0
Requires-Dist: ucdp>=0.30.1
